fleetspeak/__init__.py
fleetspeak-0.0.1.dist-info/DESCRIPTION.rst
fleetspeak-0.0.1.dist-info/METADATA
fleetspeak-0.0.1.dist-info/RECORD
fleetspeak-0.0.1.dist-info/WHEEL
fleetspeak-0.0.1.dist-info/metadata.json
fleetspeak-0.0.1.dist-info/top_level.txt
