Metadata-Version: 2.0
Name: fleetspeak
Version: 0.0.1
Summary: UNKNOWN
Home-page: https://github.com
Author: UNKNOWN
Author-email: UNKNOWN
License: Apache License, Version 2.0
Platform: UNKNOWN
Classifier: Development Status :: 3 - Alpha
Classifier: Intended Audience :: Developers
Classifier: Topic :: Software Development
Classifier: License :: OSI Approved :: Apache Software License
Classifier: Programming Language :: Python :: 2.7
Requires-Dist: futures
Requires-Dist: google-apputils
Requires-Dist: grpcio
Requires-Dist: grpcio-tools
Requires-Dist: python-gflags
Requires-Dist: six
Provides-Extra: dev
Provides-Extra: test
